fdtool/__init__.py
fdtool/__main__.py
fdtool/config.py
fdtool/fdtool.py
fdtool/modules/.gitignore
fdtool/modules/Apriori_Gen.py
fdtool/modules/Apriori_Gen.pyc
fdtool/modules/GetFDs.py
fdtool/modules/GetFDs.pyc
fdtool/modules/ObtainEquivalences.py
fdtool/modules/ObtainEquivalences.pyc
fdtool/modules/Prune.py
fdtool/modules/Prune.pyc
fdtool/modules/__init__.py
fdtool/modules/__init__.pyc
fdtool/modules/binaryRepr.py
fdtool/modules/binaryRepr.pyc
fdtool/modules/keyRun.py
fdtool/modules/keyRun.pyc
fdtool/modules/dbschema/.gitignore
fdtool/modules/dbschema/C-FSL-v1.1.txt
fdtool/modules/dbschema/MANIFEST.in
fdtool/modules/dbschema/__init__.py
fdtool/modules/dbschema/__init__.pyc
fdtool/modules/dbschema/dbschema.py
fdtool/modules/dbschema/dbschema.pyc
fdtool/modules/dbschema/Docs/keysAlg-dbschemacmd.pdf
fdtool-0.1.7.dist-info/METADATA
fdtool-0.1.7.dist-info/RECORD
fdtool-0.1.7.dist-info/WHEEL
fdtool-0.1.7.dist-info/entry_points.txt
fdtool-0.1.7.dist-info/top_level.txt
