Metadata-Version: 2.1
Name: fdtool
Version: 0.1.7
Summary: Identify functional dependencies, equivalences, and candidate keys in tabular data
Home-page: https://github.com/USEPA/FDTool/
Author: Matt Buranosky
Author-email: buranosky.matthew@epa.gov
License: CC0
Platform: UNKNOWN
